odoo/addons/stock_picking_show_return/README.rst
odoo/addons/stock_picking_show_return/__init__.py
odoo/addons/stock_picking_show_return/__manifest__.py
odoo/addons/stock_picking_show_return/i18n/de.po
odoo/addons/stock_picking_show_return/i18n/es.po
odoo/addons/stock_picking_show_return/i18n/fr.po
odoo/addons/stock_picking_show_return/i18n/it.po
odoo/addons/stock_picking_show_return/i18n/nl_NL.po
odoo/addons/stock_picking_show_return/i18n/pt.po
odoo/addons/stock_picking_show_return/i18n/pt_BR.po
odoo/addons/stock_picking_show_return/i18n/sl.po
odoo/addons/stock_picking_show_return/i18n/stock_picking_show_return.pot
odoo/addons/stock_picking_show_return/models/__init__.py
odoo/addons/stock_picking_show_return/models/stock_picking.py
odoo/addons/stock_picking_show_return/readme/CONTRIBUTORS.rst
odoo/addons/stock_picking_show_return/readme/DESCRIPTION.rst
odoo/addons/stock_picking_show_return/readme/HISTORY.rst
odoo/addons/stock_picking_show_return/readme/USAGE.rst
odoo/addons/stock_picking_show_return/static/description/icon.png
odoo/addons/stock_picking_show_return/static/description/index.html
odoo/addons/stock_picking_show_return/tests/__init__.py
odoo/addons/stock_picking_show_return/tests/test_stock_picking_show_return.py
odoo/addons/stock_picking_show_return/views/stock_picking_view.xml
odoo12_addon_stock_picking_show_return-12.0.2.0.0.dist-info/METADATA
odoo12_addon_stock_picking_show_return-12.0.2.0.0.dist-info/WHEEL
odoo12_addon_stock_picking_show_return-12.0.2.0.0.dist-info/top_level.txt
odoo12_addon_stock_picking_show_return-12.0.2.0.0.dist-info/RECORD
